[{"closestPoint":1725.4190788505525,"idLeaflet":"1152","idControl":"1157"},{"closestPoint":5787.900299415962,"idLeaflet":"2718","idControl":"1954"},{"closestPoint":5183.856909328194,"idLeaflet":"1231","idControl":"1223"},{"closestPoint":1829.5280594964775,"idLeaflet":"1930","idControl":"1929"},{"closestPoint":1499.4570916836851,"idLeaflet":"2263","idControl":"2261"},{"closestPoint":3811.6517368438426,"idLeaflet":"1005","idControl":"1011"},{"closestPoint":2914.096377816049,"idLeaflet":"946","idControl":"3250"},{"closestPoint":2644.8214460920053,"idLeaflet":"1468","idControl":"1461"},{"closestPoint":4198.862194133958,"idLeaflet":"2109","idControl":"2111"},{"closestPoint":4267.535178629828,"idLeaflet":"3348","idControl":"3354"},{"closestPoint":6336.23449943976,"idLeaflet":"118","idControl":"1406"},{"closestPoint":5877.477786299831,"idLeaflet":"555","idControl":"1445"},{"closestPoint":6332.307099632439,"idLeaflet":"1375","idControl":"1370"},{"closestPoint":3387.6377986231314,"idLeaflet":"481","idControl":"467"},{"closestPoint":3052.1935072065608,"idLeaflet":"315","idControl":"309"},{"closestPoint":4852.84913164345,"idLeaflet":"400","idControl":"384"},{"closestPoint":11498.193067059707,"idLeaflet":"70","idControl":"623"},{"closestPoint":5438.623272122729,"idLeaflet":"1228","idControl":"1217"},{"closestPoint":4070.611866510516,"idLeaflet":"578","idControl":"917"},{"closestPoint":3456.0603714744393,"idLeaflet":"541","idControl":"545"},{"closestPoint":4822.207058348582,"idLeaflet":"3148","idControl":"3156"},{"closestPoint":5661.7927563724925,"idLeaflet":"178","idControl":"177"},{"closestPoint":1654.7033608945553,"idLeaflet":"2777","idControl":"2791"},{"closestPoint":2537.352799054971,"idLeaflet":"522","idControl":"525"},{"closestPoint":1902.9040327682453,"idLeaflet":"1926","idControl":"1917"},{"closestPoint":8072.109384682925,"idLeaflet":"3096","idControl":"3092"},{"closestPoint":4798.600334114303,"idLeaflet":"1895","idControl":"1896"},{"closestPoint":5463.011375304835,"idLeaflet":"295","idControl":"3187"},{"closestPoint":3064.185806387097,"idLeaflet":"2466","idControl":"2469"},{"closestPoint":4979.555169021268,"idLeaflet":"23","idControl":"317"},{"closestPoint":2360.7772576143393,"idLeaflet":"217","idControl":"192"},{"closestPoint":1321.5995079584739,"idLeaflet":"3105","idControl":"1639"},{"closestPoint":3164.361318221171,"idLeaflet":"19","idControl":"13"},{"closestPoint":4254.24695333096,"idLeaflet":"139","idControl":"75"},{"closestPoint":3315.3405408400354,"idLeaflet":"2032","idControl":"2034"},{"closestPoint":4759.583855324184,"idLeaflet":"2195","idControl":"2194"},{"closestPoint":2317.716700884855,"idLeaflet":"1716","idControl":"1707"},{"closestPoint":9653.46857137807,"idLeaflet":"1114","idControl":"1367"},{"closestPoint":2401.890776069336,"idLeaflet":"806","idControl":"2814"},{"closestPoint":7865.976301958845,"idLeaflet":"1895","idControl":"2619"},{"closestPoint":5183.154593447656,"idLeaflet":"217","idControl":"202"},{"closestPoint":7644.077016039435,"idLeaflet":"1532","idControl":"1533"},{"closestPoint":3870.4484854989614,"idLeaflet":"1012","idControl":"1017"},{"closestPoint":13401.693058700752,"idLeaflet":"1939","idControl":"1523"},{"closestPoint":3575.5250968237615,"idLeaflet":"2611","idControl":"2609"},{"closestPoint":9499.075353312994,"idLeaflet":"1487","idControl":"165"},{"closestPoint":3271.0945651108286,"idLeaflet":"2992","idControl":"2989"},{"closestPoint":2223.695033415656,"idLeaflet":"823","idControl":"2882"},{"closestPoint":1254.9281236217676,"idLeaflet":"765","idControl":"766"},{"closestPoint":1841.5636292411104,"idLeaflet":"2781","idControl":"2780"},{"closestPoint":1345.2316259852025,"idLeaflet":"610","idControl":"614"},{"closestPoint":973.0820191462976,"idLeaflet":"1840","idControl":"1846"},{"closestPoint":2225.7001906582077,"idLeaflet":"913","idControl":"912"},{"closestPoint":3949.9585683707987,"idLeaflet":"2806","idControl":"2807"},{"closestPoint":7638.016085901555,"idLeaflet":"236","idControl":"241"},{"closestPoint":4016.2928532911524,"idLeaflet":"3091","idControl":"3082"},{"closestPoint":3209.3044039349957,"idLeaflet":"166","idControl":"168"},{"closestPoint":3959.27192961331,"idLeaflet":"2387","idControl":"2385"},{"closestPoint":5692.975283069852,"idLeaflet":"2935","idControl":"2933"},{"closestPoint":2774.7793909167644,"idLeaflet":"2390","idControl":"2050"},{"closestPoint":4002.160719623702,"idLeaflet":"1902","idControl":"1898"},{"closestPoint":3195.3434867257106,"idLeaflet":"343","idControl":"337"},{"closestPoint":2036.1629213100255,"idLeaflet":"3227","idControl":"3225"},{"closestPoint":2872.3567667233865,"idLeaflet":"757","idControl":"2367"},{"closestPoint":2976.429303159578,"idLeaflet":"2188","idControl":"2186"},{"closestPoint":6142.886020687931,"idLeaflet":"35","idControl":"1103"},{"closestPoint":3316.155912265897,"idLeaflet":"349","idControl":"355"},{"closestPoint":15124.73373657137,"idLeaflet":"2663","idControl":"1428"},{"closestPoint":2242.9673018448652,"idLeaflet":"517","idControl":"514"},{"closestPoint":5234.019776550625,"idLeaflet":"2195","idControl":"2187"},{"closestPoint":2843.711266643556,"idLeaflet":"2391","idControl":"2019"},{"closestPoint":4277.799811350285,"idLeaflet":"522","idControl":"526"},{"closestPoint":8013.119192754698,"idLeaflet":"1987","idControl":"1999"},{"closestPoint":5064.509957661739,"idLeaflet":"2291","idControl":"2292"},{"closestPoint":5839.102010334629,"idLeaflet":"19","idControl":"20"},{"closestPoint":4457.324656678892,"idLeaflet":"1721","idControl":"519"},{"closestPoint":9697.574070438099,"idLeaflet":"3297","idControl":"3296"},{"closestPoint":8729.45993299477,"idLeaflet":"3246","idControl":"498"},{"closestPoint":3063.792409143977,"idLeaflet":"627","idControl":"3075"},{"closestPoint":3772.9835346683767,"idLeaflet":"1609","idControl":"1601"},{"closestPoint":4510.166282402392,"idLeaflet":"2413","idControl":"3010"},{"closestPoint":11226.32354675543,"idLeaflet":"3064","idControl":"3074"},{"closestPoint":4512.207284508093,"idLeaflet":"725","idControl":"528"},{"closestPoint":6884.586250413337,"idLeaflet":"1408","idControl":"924"},{"closestPoint":3583.7356794776024,"idLeaflet":"312","idControl":"308"},{"closestPoint":3490.965353371368,"idLeaflet":"510","idControl":"373"},{"closestPoint":1610.3346906754948,"idLeaflet":"2313","idControl":"2312"},{"closestPoint":8043.982631795939,"idLeaflet":"442","idControl":"915"},{"closestPoint":3984.097716950308,"idLeaflet":"1457","idControl":"879"},{"closestPoint":6771.453230265384,"idLeaflet":"2961","idControl":"2956"},{"closestPoint":3665.6132827820106,"idLeaflet":"372","idControl":"2182"},{"closestPoint":4190.254258790517,"idLeaflet":"392","idControl":"3058"},{"closestPoint":5144.647329536625,"idLeaflet":"315","idControl":"304"},{"closestPoint":5444.604663394171,"idLeaflet":"1849","idControl":"1856"},{"closestPoint":3253.9784106363177,"idLeaflet":"1956","idControl":"2610"},{"closestPoint":937.9844533714961,"idLeaflet":"667","idControl":"662"},{"closestPoint":5023.54081625476,"idLeaflet":"3177","idControl":"3180"},{"closestPoint":6410.26290084669,"idLeaflet":"1449","idControl":"1701"},{"closestPoint":1090.7472083655891,"idLeaflet":"1492","idControl":"1489"},{"closestPoint":3101.7897116521226,"idLeaflet":"753","idControl":"749"},{"closestPoint":2838.2714332957603,"idLeaflet":"919","idControl":"2936"},{"closestPoint":3936.5394493395333,"idLeaflet":"975","idControl":"1685"},{"closestPoint":3144.3949194102665,"idLeaflet":"1563","idControl":"1565"},{"closestPoint":4482.834129530889,"idLeaflet":"2635","idControl":"2637"},{"closestPoint":4469.725330842083,"idLeaflet":"81","idControl":"71"},{"closestPoint":5449.673928001959,"idLeaflet":"3145","idControl":"3140"},{"closestPoint":4086.1382498271673,"idLeaflet":"533","idControl":"535"},{"closestPoint":8124.017768865223,"idLeaflet":"1328","idControl":"1316"},{"closestPoint":6347.769670121785,"idLeaflet":"422","idControl":"420"},{"closestPoint":4808.489059663762,"idLeaflet":"457","idControl":"462"},{"closestPoint":8431.574161151691,"idLeaflet":"1228","idControl":"1220"},{"closestPoint":5254.632342040074,"idLeaflet":"351","idControl":"339"},{"closestPoint":2688.3556596093526,"idLeaflet":"2512","idControl":"2513"},{"closestPoint":7466.067384766845,"idLeaflet":"2061","idControl":"2065"},{"closestPoint":3538.4395575846092,"idLeaflet":"1819","idControl":"1818"},{"closestPoint":7222.129364445942,"idLeaflet":"1547","idControl":"1548"},{"closestPoint":1388.0347795900566,"idLeaflet":"2671","idControl":"2670"},{"closestPoint":5709.781874332832,"idLeaflet":"2985","idControl":"2982"},{"closestPoint":4806.609385506554,"idLeaflet":"1063","idControl":"1086"},{"closestPoint":3254.3672446897494,"idLeaflet":"3317","idControl":"3374"},{"closestPoint":4208.642726534433,"idLeaflet":"2935","idControl":"644"},{"closestPoint":10036.310580793333,"idLeaflet":"1012","idControl":"3285"},{"closestPoint":2592.6538591634053,"idLeaflet":"2354","idControl":"2357"},{"closestPoint":5468.722817811882,"idLeaflet":"3111","idControl":"3112"},{"closestPoint":7250.837438586641,"idLeaflet":"84","idControl":"2681"},{"closestPoint":2762.7319494660287,"idLeaflet":"1231","idControl":"1225"},{"closestPoint":4691.774318770679,"idLeaflet":"867","idControl":"862"},{"closestPoint":5392.7638703196335,"idLeaflet":"2694","idControl":"1162"},{"closestPoint":4179.2612567871565,"idLeaflet":"1322","idControl":"3327"},{"closestPoint":2846.208990388867,"idLeaflet":"2680","idControl":"2688"},{"closestPoint":3063.9211934172477,"idLeaflet":"3371","idControl":"3376"},{"closestPoint":1778.020777337485,"idLeaflet":"45","idControl":"49"},{"closestPoint":3651.2943525332657,"idLeaflet":"1885","idControl":"3127"},{"closestPoint":10940.479030977292,"idLeaflet":"2752","idControl":"2750"},{"closestPoint":4723.606654023098,"idLeaflet":"1218","idControl":"1248"},{"closestPoint":3171.167710825463,"idLeaflet":"3019","idControl":"3012"},{"closestPoint":7853.893413070095,"idLeaflet":"2276","idControl":"212"},{"closestPoint":3023.1183920363583,"idLeaflet":"829","idControl":"825"},{"closestPoint":9721.570992988945,"idLeaflet":"2883","idControl":"1010"},{"closestPoint":2867.0444881290814,"idLeaflet":"2622","idControl":"2621"},{"closestPoint":4234.388323619964,"idLeaflet":"3019","idControl":"3020"},{"closestPoint":3261.4077529030365,"idLeaflet":"1343","idControl":"1349"},{"closestPoint":5158.482265862423,"idLeaflet":"2752","idControl":"2751"},{"closestPoint":5982.1477246668865,"idLeaflet":"70","idControl":"64"},{"closestPoint":6098.683735558104,"idLeaflet":"3139","idControl":"3144"},{"closestPoint":3735.7501976623503,"idLeaflet":"3091","idControl":"3081"},{"closestPoint":5289.592678262342,"idLeaflet":"1138","idControl":"1134"},{"closestPoint":3396.046996176363,"idLeaflet":"1293","idControl":"2085"},{"closestPoint":6577.77420348882,"idLeaflet":"2087","idControl":"2080"},{"closestPoint":2523.444970899313,"idLeaflet":"349","idControl":"353"},{"closestPoint":2397.1571800197285,"idLeaflet":"1040","idControl":"1041"},{"closestPoint":7662.200807764082,"idLeaflet":"1138","idControl":"1135"},{"closestPoint":2122.2084749071782,"idLeaflet":"2673","idControl":"2675"},{"closestPoint":6331.811858827586,"idLeaflet":"40","idControl":"37"},{"closestPoint":5318.432953560254,"idLeaflet":"1298","idControl":"1297"},{"closestPoint":9588.043462033782,"idLeaflet":"2857","idControl":"2849"},{"closestPoint":5012.2677562970985,"idLeaflet":"3228","idControl":"3224"},{"closestPoint":1920.4349310964956,"idLeaflet":"441","idControl":"1887"},{"closestPoint":7133.329646718707,"idLeaflet":"2996","idControl":"3000"},{"closestPoint":5608.679652826147,"idLeaflet":"867","idControl":"2527"},{"closestPoint":3002.9479498030346,"idLeaflet":"894","idControl":"884"},{"closestPoint":6054.619393861884,"idLeaflet":"650","idControl":"657"},{"closestPoint":3163.927683432566,"idLeaflet":"1976","idControl":"1975"},{"closestPoint":6567.144197988963,"idLeaflet":"1305","idControl":"1296"},{"closestPoint":3332.488130186639,"idLeaflet":"887","idControl":"885"},{"closestPoint":5508.517148999502,"idLeaflet":"2949","idControl":"2946"},{"closestPoint":1625.764504592183,"idLeaflet":"3069","idControl":"3073"},{"closestPoint":7091.093374099615,"idLeaflet":"1290","idControl":"701"},{"closestPoint":4519.249070417267,"idLeaflet":"3158","idControl":"3160"},{"closestPoint":4496.451565300461,"idLeaflet":"2231","idControl":"1911"},{"closestPoint":3024.350054064166,"idLeaflet":"2604","idControl":"2605"},{"closestPoint":3081.239859267421,"idLeaflet":"2342","idControl":"2332"},{"closestPoint":8629.71154592617,"idLeaflet":"1282","idControl":"3276"},{"closestPoint":4437.920743197767,"idLeaflet":"1838","idControl":"1842"},{"closestPoint":6721.316062477729,"idLeaflet":"2342","idControl":"18"},{"closestPoint":4749.558467238683,"idLeaflet":"138","idControl":"136"},{"closestPoint":4510.490596073401,"idLeaflet":"1457","idControl":"1460"},{"closestPoint":3703.4178722703587,"idLeaflet":"454","idControl":"132"},{"closestPoint":1648.2106047410155,"idLeaflet":"570","idControl":"565"},{"closestPoint":3106.1843212818976,"idLeaflet":"4","idControl":"10"},{"closestPoint":1932.848813260121,"idLeaflet":"2758","idControl":"2772"},{"closestPoint":3111.59244493757,"idLeaflet":"3166","idControl":"3173"},{"closestPoint":2918.837050705386,"idLeaflet":"1824","idControl":"1830"},{"closestPoint":9711.050789164285,"idLeaflet":"3247","idControl":"3245"},{"closestPoint":14426.230042923957,"idLeaflet":"608","idControl":"1137"},{"closestPoint":2789.535624763224,"idLeaflet":"925","idControl":"1347"},{"closestPoint":3263.8328639265865,"idLeaflet":"1713","idControl":"437"},{"closestPoint":3965.0733542150547,"idLeaflet":"845","idControl":"847"},{"closestPoint":12525.655135950945,"idLeaflet":"2057","idControl":"2062"},{"closestPoint":8506.384726378312,"idLeaflet":"264","idControl":"2930"},{"closestPoint":4672.037797981975,"idLeaflet":"393","idControl":"405"},{"closestPoint":7334.252345949985,"idLeaflet":"1255","idControl":"1266"},{"closestPoint":2165.710059482977,"idLeaflet":"806","idControl":"800"},{"closestPoint":2264.8542013509573,"idLeaflet":"2061","idControl":"2064"},{"closestPoint":7074.393989840793,"idLeaflet":"2285","idControl":"697"},{"closestPoint":6409.775707677778,"idLeaflet":"2310","idControl":"2302"},{"closestPoint":3528.0717613066236,"idLeaflet":"1301","idControl":"1302"},{"closestPoint":8815.189017539733,"idLeaflet":"2560","idControl":"2474"},{"closestPoint":5947.270069605669,"idLeaflet":"2975","idControl":"2973"},{"closestPoint":2339.665268254711,"idLeaflet":"1920","idControl":"8"},{"closestPoint":3296.9024403170556,"idLeaflet":"2624","idControl":"2625"},{"closestPoint":1341.0075660391446,"idLeaflet":"1941","idControl":"1943"},{"closestPoint":5552.35963170586,"idLeaflet":"1336","idControl":"2836"},{"closestPoint":2940.3080890144074,"idLeaflet":"2777","idControl":"844"},{"closestPoint":885.8953334416586,"idLeaflet":"3019","idControl":"3036"},{"closestPoint":4866.7851123445025,"idLeaflet":"720","idControl":"728"},{"closestPoint":5842.013899441023,"idLeaflet":"2889","idControl":"2887"},{"closestPoint":947.1511417492088,"idLeaflet":"1734","idControl":"1753"},{"closestPoint":3721.635709631372,"idLeaflet":"2271","idControl":"2270"},{"closestPoint":4198.309684121009,"idLeaflet":"987","idControl":"638"},{"closestPoint":5316.825863741406,"idLeaflet":"293","idControl":"2059"},{"closestPoint":3378.7847359033967,"idLeaflet":"481","idControl":"468"},{"closestPoint":2914.3204317663462,"idLeaflet":"2654","idControl":"2653"},{"closestPoint":2769.7463153881536,"idLeaflet":"1016","idControl":"1023"},{"closestPoint":5594.304407368926,"idLeaflet":"1606","idControl":"1607"},{"closestPoint":1896.8473245275593,"idLeaflet":"2774","idControl":"2766"},{"closestPoint":4703.347102368827,"idLeaflet":"2118","idControl":"2112"},{"closestPoint":3959.9066212097982,"idLeaflet":"2339","idControl":"2278"},{"closestPoint":4793.4517654556485,"idLeaflet":"299","idControl":"297"},{"closestPoint":4180.945947683286,"idLeaflet":"343","idControl":"340"},{"closestPoint":4081.287541499101,"idLeaflet":"2266","idControl":"542"},{"closestPoint":3788.213207434312,"idLeaflet":"2857","idControl":"2848"},{"closestPoint":3590.2262713679925,"idLeaflet":"2914","idControl":"314"},{"closestPoint":7376.884522116863,"idLeaflet":"3145","idControl":"3363"},{"closestPoint":1359.3907969788334,"idLeaflet":"9","idControl":"2"},{"closestPoint":7001.734346393739,"idLeaflet":"2083","idControl":"160"},{"closestPoint":5602.553220957734,"idLeaflet":"2445","idControl":"2446"},{"closestPoint":4122.400044713795,"idLeaflet":"1318","idControl":"3326"},{"closestPoint":5278.658421870787,"idLeaflet":"1404","idControl":"1400"},{"closestPoint":7480.911843088286,"idLeaflet":"3297","idControl":"3290"},{"closestPoint":6005.330237852723,"idLeaflet":"2293","idControl":"2298"},{"closestPoint":5284.902855060332,"idLeaflet":"1295","idControl":"3280"},{"closestPoint":5481.556504677436,"idLeaflet":"214","idControl":"221"},{"closestPoint":3519.8664954389137,"idLeaflet":"1040","idControl":"1045"},{"closestPoint":6457.742066612025,"idLeaflet":"600","idControl":"156"},{"closestPoint":4312.504821930701,"idLeaflet":"1430","idControl":"1432"},{"closestPoint":5175.574937750391,"idLeaflet":"2633","idControl":"369"},{"closestPoint":3722.7383200909558,"idLeaflet":"139","idControl":"143"},{"closestPoint":5054.283358332086,"idLeaflet":"1282","idControl":"1281"},{"closestPoint":2851.4407952764427,"idLeaflet":"253","idControl":"2378"},{"closestPoint":5323.208263224676,"idLeaflet":"2645","idControl":"2648"},{"closestPoint":1875.0332137799728,"idLeaflet":"1976","idControl":"1981"},{"closestPoint":1938.35048393355,"idLeaflet":"1380","idControl":"1386"},{"closestPoint":1460.1285309941238,"idLeaflet":"1415","idControl":"1412"},{"closestPoint":13346.854175912407,"idLeaflet":"2141","idControl":"2145"},{"closestPoint":5801.197651537392,"idLeaflet":"490","idControl":"496"},{"closestPoint":7525.361100320416,"idLeaflet":"1254","idControl":"1263"},{"closestPoint":1345.6357380119086,"idLeaflet":"3019","idControl":"3024"},{"closestPoint":1325.2538917360546,"idLeaflet":"1743","idControl":"1736"},{"closestPoint":3092.913739182926,"idLeaflet":"1502","idControl":"1501"},{"closestPoint":3292.5207105015106,"idLeaflet":"1827","idControl":"1309"},{"closestPoint":5634.3820413409685,"idLeaflet":"1807","idControl":"1813"},{"closestPoint":1887.497046540609,"idLeaflet":"1393","idControl":"1391"},{"closestPoint":3982.5738011325193,"idLeaflet":"3342","idControl":"3337"},{"closestPoint":9122.031593067586,"idLeaflet":"387","idControl":"385"},{"closestPoint":1503.2145382001052,"idLeaflet":"1891","idControl":"1892"},{"closestPoint":5960.266288313935,"idLeaflet":"925","idControl":"1344"},{"closestPoint":1209.3983007215338,"idLeaflet":"2132","idControl":"2128"},{"closestPoint":4679.4052899975695,"idLeaflet":"1012","idControl":"1029"},{"closestPoint":5939.183880222478,"idLeaflet":"3064","idControl":"3060"},{"closestPoint":3013.588249656074,"idLeaflet":"2271","idControl":"2269"},{"closestPoint":3010.4285955626756,"idLeaflet":"3132","idControl":"3129"},{"closestPoint":6772.436340005402,"idLeaflet":"907","idControl":"911"},{"closestPoint":4803.685724335666,"idLeaflet":"235","idControl":"2970"},{"closestPoint":5019.329465216053,"idLeaflet":"1723","idControl":"1719"},{"closestPoint":2195.1044469625663,"idLeaflet":"806","idControl":"2815"},{"closestPoint":7947.250546026477,"idLeaflet":"1838","idControl":"1831"},{"closestPoint":7827.8776574041785,"idLeaflet":"2927","idControl":"2921"},{"closestPoint":8685.239466760933,"idLeaflet":"162","idControl":"158"},{"closestPoint":3372.349365351604,"idLeaflet":"2307","idControl":"2304"},{"closestPoint":7451.043485953495,"idLeaflet":"178","idControl":"2152"},{"closestPoint":4872.469924117453,"idLeaflet":"2482","idControl":"2620"},{"closestPoint":8389.99781809783,"idLeaflet":"3244","idControl":"3240"},{"closestPoint":3782.720221550994,"idLeaflet":"2903","idControl":"2909"},{"closestPoint":9550.362616564491,"idLeaflet":"3063","idControl":"386"},{"closestPoint":3564.686465281226,"idLeaflet":"2636","idControl":"259"},{"closestPoint":6144.870760589382,"idLeaflet":"671","idControl":"2036"},{"closestPoint":6473.332235898388,"idLeaflet":"2093","idControl":"244"},{"closestPoint":2915.958918739176,"idLeaflet":"3008","idControl":"3022"},{"closestPoint":4366.069674155548,"idLeaflet":"1956","idControl":"811"},{"closestPoint":4412.608059914652,"idLeaflet":"1132","idControl":"1128"},{"closestPoint":9588.672175366433,"idLeaflet":"2179","idControl":"172"},{"closestPoint":8367.266528512495,"idLeaflet":"1301","idControl":"3333"},{"closestPoint":2527.6585148652966,"idLeaflet":"522","idControl":"513"},{"closestPoint":3321.7525733785924,"idLeaflet":"1430","idControl":"1437"},{"closestPoint":4534.385358582761,"idLeaflet":"220","idControl":"200"},{"closestPoint":2575.6501419603037,"idLeaflet":"178","idControl":"173"},{"closestPoint":6627.665097081862,"idLeaflet":"782","idControl":"1071"},{"closestPoint":993.4752544975518,"idLeaflet":"806","idControl":"801"},{"closestPoint":8483.363574422827,"idLeaflet":"2086","idControl":"2082"},{"closestPoint":5946.83692018258,"idLeaflet":"390","idControl":"382"},{"closestPoint":16037.940019265852,"idLeaflet":"2663","idControl":"1425"},{"closestPoint":7780.088503272087,"idLeaflet":"2120","idControl":"434"},{"closestPoint":5247.166425075769,"idLeaflet":"2221","idControl":"2211"},{"closestPoint":1766.3347576405852,"idLeaflet":"3263","idControl":"3261"},{"closestPoint":3911.9335343945354,"idLeaflet":"96","idControl":"2475"},{"closestPoint":2734.328480973924,"idLeaflet":"693","idControl":"1907"},{"closestPoint":4409.124252159535,"idLeaflet":"1408","idControl":"923"},{"closestPoint":943.3336687310314,"idLeaflet":"1977","idControl":"1982"},{"closestPoint":2398.9622752113355,"idLeaflet":"2313","idControl":"2314"},{"closestPoint":4211.202222616302,"idLeaflet":"2810","idControl":"2804"},{"closestPoint":4212.2461421271655,"idLeaflet":"2105","idControl":"2102"},{"closestPoint":1210.0609748899133,"idLeaflet":"1956","idControl":"1955"},{"closestPoint":15839.580119093529,"idLeaflet":"1600","idControl":"2962"},{"closestPoint":3357.43893641179,"idLeaflet":"3096","idControl":"3095"},{"closestPoint":1999.1694939339434,"idLeaflet":"2581","idControl":"2584"},{"closestPoint":5711.565469535019,"idLeaflet":"207","idControl":"209"},{"closestPoint":3568.193203241343,"idLeaflet":"140","idControl":"461"},{"closestPoint":969.6231016493576,"idLeaflet":"189","idControl":"183"},{"closestPoint":3939.876496303397,"idLeaflet":"2850","idControl":"291"},{"closestPoint":4413.907920411974,"idLeaflet":"3032","idControl":"3033"},{"closestPoint":6163.385871015072,"idLeaflet":"1097","idControl":"1099"},{"closestPoint":6543.420211677312,"idLeaflet":"377","idControl":"363"},{"closestPoint":8859.591634498916,"idLeaflet":"489","idControl":"494"},{"closestPoint":2217.750482499295,"idLeaflet":"2195","idControl":"2200"},{"closestPoint":845.7107319932157,"idLeaflet":"3317","idControl":"3313"},{"closestPoint":5104.038423790696,"idLeaflet":"1180","idControl":"1185"},{"closestPoint":2516.763530009549,"idLeaflet":"2057","idControl":"2063"},{"closestPoint":4244.176980249568,"idLeaflet":"2614","idControl":"1009"},{"closestPoint":5121.1862838438565,"idLeaflet":"3348","idControl":"3350"},{"closestPoint":1875.6201020798867,"idLeaflet":"2282","idControl":"2274"},{"closestPoint":2845.203283631475,"idLeaflet":"943","idControl":"938"},{"closestPoint":4818.310883083388,"idLeaflet":"3105","idControl":"1672"},{"closestPoint":4377.165957373079,"idLeaflet":"829","idControl":"1088"},{"closestPoint":962.748101549773,"idLeaflet":"2291","idControl":"2289"},{"closestPoint":3561.505218843832,"idLeaflet":"516","idControl":"524"},{"closestPoint":3351.356419932887,"idLeaflet":"2453","idControl":"2608"},{"closestPoint":6951.253800138806,"idLeaflet":"2109","idControl":"1072"},{"closestPoint":4726.640828873555,"idLeaflet":"351","idControl":"352"},{"closestPoint":3387.6400137449623,"idLeaflet":"968","idControl":"970"},{"closestPoint":4642.915357839609,"idLeaflet":"174","idControl":"179"},{"closestPoint":2153.3508871565855,"idLeaflet":"2173","idControl":"2160"},{"closestPoint":9129.708909519843,"idLeaflet":"489","idControl":"495"},{"closestPoint":4362.83752567302,"idLeaflet":"2032","idControl":"1053"},{"closestPoint":5724.41703706555,"idLeaflet":"1906","idControl":"1904"},{"closestPoint":3844.3250160560524,"idLeaflet":"2317","idControl":"2315"},{"closestPoint":3338.9993705779857,"idLeaflet":"3192","idControl":"3185"},{"closestPoint":2154.9116264741715,"idLeaflet":"1776","idControl":"1778"},{"closestPoint":4060.0960240563063,"idLeaflet":"538","idControl":"539"},{"closestPoint":3468.9337401239377,"idLeaflet":"351","idControl":"350"},{"closestPoint":2892.48536376951,"idLeaflet":"2614","idControl":"2616"},{"closestPoint":9136.545896473386,"idLeaflet":"1231","idControl":"1247"},{"closestPoint":5555.331050453212,"idLeaflet":"578","idControl":"2520"},{"closestPoint":1978.5724873880533,"idLeaflet":"315","idControl":"305"},{"closestPoint":9240.42835900532,"idLeaflet":"421","idControl":"3346"},{"closestPoint":12022.065711691344,"idLeaflet":"1231","idControl":"1224"},{"closestPoint":4250.687007722657,"idLeaflet":"573","idControl":"576"},{"closestPoint":2798.416738329856,"idLeaflet":"2282","idControl":"2267"},{"closestPoint":5730.468017087626,"idLeaflet":"815","idControl":"820"},{"closestPoint":12768.603155259412,"idLeaflet":"58","idControl":"55"},{"closestPoint":5937.243614523514,"idLeaflet":"2037","idControl":"2031"},{"closestPoint":3733.6811076695662,"idLeaflet":"3124","idControl":"3116"},{"closestPoint":3259.309526158909,"idLeaflet":"3343","idControl":"3336"},{"closestPoint":9262.670331753501,"idLeaflet":"2560","idControl":"2561"},{"closestPoint":4780.299857537362,"idLeaflet":"362","idControl":"361"},{"closestPoint":3168.63183227116,"idLeaflet":"2375","idControl":"2366"},{"closestPoint":1870.478326214412,"idLeaflet":"3166","idControl":"3165"},{"closestPoint":5092.554729624974,"idLeaflet":"1325","idControl":"1304"},{"closestPoint":6481.517093816835,"idLeaflet":"1547","idControl":"1549"},{"closestPoint":4663.621261320722,"idLeaflet":"1807","idControl":"1808"},{"closestPoint":3405.6336146476506,"idLeaflet":"1254","idControl":"1272"},{"closestPoint":6339.98925766545,"idLeaflet":"3264","idControl":"11"},{"closestPoint":4364.892422704504,"idLeaflet":"795","idControl":"3179"},{"closestPoint":5094.950671373471,"idLeaflet":"791","idControl":"3059"},{"closestPoint":10682.11463143282,"idLeaflet":"2317","idControl":"2957"},{"closestPoint":3046.3904134251825,"idLeaflet":"1149","idControl":"1160"},{"closestPoint":3442.6535937132103,"idLeaflet":"2977","idControl":"2967"},{"closestPoint":4020.731708784914,"idLeaflet":"1387","idControl":"1390"},{"closestPoint":7003.880229634159,"idLeaflet":"2178","idControl":"2174"},{"closestPoint":2935.9097933678804,"idLeaflet":"2425","idControl":"2411"},{"closestPoint":2108.4741870198977,"idLeaflet":"3105","idControl":"1169"},{"closestPoint":3037.945283640958,"idLeaflet":"3014","idControl":"3035"},{"closestPoint":3301.239852860154,"idLeaflet":"1434","idControl":"1433"},{"closestPoint":6643.325475092082,"idLeaflet":"257","idControl":"260"},{"closestPoint":4773.243165545534,"idLeaflet":"2903","idControl":"2906"},{"closestPoint":2502.5623124861454,"idLeaflet":"1414","idControl":"1411"},{"closestPoint":7020.461435741057,"idLeaflet":"660","idControl":"652"},{"closestPoint":2296.3228464882745,"idLeaflet":"2743","idControl":"2744"},{"closestPoint":6663.760878528816,"idLeaflet":"2141","idControl":"2137"},{"closestPoint":2762.77815196724,"idLeaflet":"2523","idControl":"2526"},{"closestPoint":2583.208787385121,"idLeaflet":"3253","idControl":"1213"},{"closestPoint":2347.0422553607104,"idLeaflet":"752","idControl":"2349"},{"closestPoint":8106.309845875972,"idLeaflet":"2661","idControl":"2669"},{"closestPoint":5565.108855795487,"idLeaflet":"1058","idControl":"1052"},{"closestPoint":9619.015244379503,"idLeaflet":"1251","idControl":"1252"},{"closestPoint":2578.821653062479,"idLeaflet":"3170","idControl":"3174"},{"closestPoint":6694.906240797204,"idLeaflet":"1032","idControl":"1026"},{"closestPoint":5887.078861489484,"idLeaflet":"676","idControl":"1488"},{"closestPoint":3450.4222459423377,"idLeaflet":"155","idControl":"154"},{"closestPoint":5071.11518341141,"idLeaflet":"1571","idControl":"1575"},{"closestPoint":1809.781872405382,"idLeaflet":"806","idControl":"2818"},{"closestPoint":1661.8978198544703,"idLeaflet":"3262","idControl":"3271"},{"closestPoint":3920.2662927261836,"idLeaflet":"3195","idControl":"3206"},{"closestPoint":2351.8031984789745,"idLeaflet":"1180","idControl":"1206"},{"closestPoint":13958.709297268226,"idLeaflet":"3096","idControl":"3094"},{"closestPoint":7329.854997937165,"idLeaflet":"887","idControl":"883"},{"closestPoint":4156.109146300177,"idLeaflet":"951","idControl":"962"},{"closestPoint":1596.381620925801,"idLeaflet":"1286","idControl":"1288"},{"closestPoint":2847.026661842584,"idLeaflet":"1032","idControl":"1019"},{"closestPoint":8222.283734135266,"idLeaflet":"2459","idControl":"3325"}]